shove_sqlalchemy/__init__.py
shove_sqlalchemy/cache.py
shove_sqlalchemy/store.py
shove_sqlalchemy/test/__init__.py
shove_sqlalchemy/test/test_sqacache.py
shove_sqlalchemy/test/test_sqastore.py
shove_sqlalchemy-0.1.0.dist-info/DESCRIPTION.rst
shove_sqlalchemy-0.1.0.dist-info/METADATA
shove_sqlalchemy-0.1.0.dist-info/RECORD
shove_sqlalchemy-0.1.0.dist-info/WHEEL
shove_sqlalchemy-0.1.0.dist-info/entry_points.txt
shove_sqlalchemy-0.1.0.dist-info/metadata.json
shove_sqlalchemy-0.1.0.dist-info/pbr.json
shove_sqlalchemy-0.1.0.dist-info/top_level.txt
