Metadata-Version: 2.0
Name: shove-sqlalchemy
Version: 0.1.0
Summary: Common object storage frontend using SQLAlchemy
Home-page: https://bitbucket.org/lcrees/shove-sqlalchemy
Author: L. C. Rees
Author-email: lcrees@gmail.com
License: BSD
Keywords: object storage persistence database sqlalchemy rdms
Platform: UNKNOWN
Classifier: Development Status :: 4 - Beta
Classifier: Environment :: Web Environment
Classifier: License :: OSI Approved :: BSD License
Classifier: Operating System :: OS Independent
Classifier: Programming Language :: Python
Classifier: Topic :: Database :: Front-Ends
Classifier: Programming Language :: Python
Classifier: Programming Language :: Python :: 2.6
Classifier: Programming Language :: Python :: 2.7
Requires-Dist: shove (>=0.6.4)
Requires-Dist: sqlalchemy (>=0.4)
